pyrit/__init__.py
pyrit/show_versions.py
pyrit/analytics/__init__.py
pyrit/analytics/conversation_analytics.py
pyrit/analytics/result_analysis.py
pyrit/analytics/text_matching.py
pyrit/auth/__init__.py
pyrit/auth/auth_config.py
pyrit/auth/authenticator.py
pyrit/auth/azure_auth.py
pyrit/auth/azure_storage_auth.py
pyrit/auxiliary_attacks/__init__.py
pyrit/auxiliary_attacks/gcg/attack/__init__.py
pyrit/auxiliary_attacks/gcg/attack/base/__init__.py
pyrit/auxiliary_attacks/gcg/attack/base/attack_manager.py
pyrit/auxiliary_attacks/gcg/attack/gcg/__init__.py
pyrit/auxiliary_attacks/gcg/attack/gcg/gcg_attack.py
pyrit/auxiliary_attacks/gcg/experiments/README.md
pyrit/auxiliary_attacks/gcg/experiments/__init__.py
pyrit/auxiliary_attacks/gcg/experiments/log.py
pyrit/auxiliary_attacks/gcg/experiments/run.py
pyrit/auxiliary_attacks/gcg/experiments/train.py
pyrit/auxiliary_attacks/gcg/experiments/configs/individual_llama_2.yaml
pyrit/auxiliary_attacks/gcg/experiments/configs/individual_llama_3.yaml
pyrit/auxiliary_attacks/gcg/experiments/configs/individual_mistral.yaml
pyrit/auxiliary_attacks/gcg/experiments/configs/individual_phi_3_mini.yaml
pyrit/auxiliary_attacks/gcg/experiments/configs/individual_vicuna.yaml
pyrit/auxiliary_attacks/gcg/experiments/configs/transfer_all_models.yaml
pyrit/auxiliary_attacks/gcg/experiments/configs/transfer_llama_2.yaml
pyrit/auxiliary_attacks/gcg/experiments/configs/transfer_llama_3.yaml
pyrit/auxiliary_attacks/gcg/experiments/configs/transfer_mistral.yaml
pyrit/auxiliary_attacks/gcg/experiments/configs/transfer_phi_3_mini.yaml
pyrit/auxiliary_attacks/gcg/experiments/configs/transfer_vicuna.yaml
pyrit/auxiliary_attacks/gcg/src/Dockerfile
pyrit/auxiliary_attacks/gcg/src/conda_dependencies.yaml
pyrit/chat_message_normalizer/__init__.py
pyrit/chat_message_normalizer/chat_message_nop.py
pyrit/chat_message_normalizer/chat_message_normalizer.py
pyrit/chat_message_normalizer/chat_message_normalizer_chatml.py
pyrit-0.10.0.dist-info/licenses/LICENSE
pyrit-0.10.0.dist-info/licenses/NOTICE.txt
pyrit-0.10.0.dist-info/METADATA
pyrit-0.10.0.dist-info/WHEEL
pyrit-0.10.0.dist-info/entry_points.txt
pyrit-0.10.0.dist-info/top_level.txt
pyrit-0.10.0.dist-info/RECORD
